mass_archive/__main__.py
mass_archive-0.0.1.dist-info/licenses/LICENSE
mass_archive-0.0.1.dist-info/METADATA
mass_archive-0.0.1.dist-info/WHEEL
mass_archive-0.0.1.dist-info/entry_points.txt
mass_archive-0.0.1.dist-info/top_level.txt
mass_archive-0.0.1.dist-info/RECORD
