Metadata-Version: 2.4
Name: mass_archive
Version: 0.0.1
Maintainer-email: Christian Heinrich <christian.heinrich@cmlh.id.au>
License-Expression: GPL-3.0-only
Keywords: archive,archiveis,wayback
License-File: LICENSE
Requires-Dist: requests
Requires-Dist: archiveis
Provides-Extra: dev
Requires-Dist: build; extra == "dev"
Requires-Dist: twine; extra == "dev"
Dynamic: license-file
